{"stat.flyOneCm":26304,"stat.walkOneCm":9051,"stat.jump":52,"stat.swimOneCm":250,"stat.useItem.minecraft.sapling":8,"stat.playOneMinute":10305,"stat.useItem.minecraft.flint_and_steel":28,"stat.leaveGame":1,"stat.sneakTime":209,"stat.useItem.minecraft.wheat_seeds":2,"stat.crouchOneCm":42,"stat.timeSinceDeath":10305,"stat.useItem.cm.copper_ingot_hoe":1,"stat.useItem.minecraft.obsidian":19,"stat.useItem.minecraft.dirt":10,"stat.sprintOneCm":4650,"stat.useItem.minecraft.dye":113,"stat.diveOneCm":2506}